setup.cfg
setup.py
sampleKafka/__init__.py
sampleKafka/sample.py
sampleKafka/common/__init__.py
sampleKafka/common/utils/Configuration.py
sampleKafka/common/utils/__init__.py
sampleKafka/consumer/__init__.py
sampleKafka/consumer/consumer.py
sampleKafka/consumer/utils/__init__.py
sampleKafka/consumer/utils/util.py
sampleKafka/producer/__init__.py
sampleKafka/producer/producer1.py
sampleKafka/producer/producer2.py
testUploadMyPython.egg-info/PKG-INFO
testUploadMyPython.egg-info/SOURCES.txt
testUploadMyPython.egg-info/dependency_links.txt
testUploadMyPython.egg-info/top_level.txt