Metadata-Version: 1.1
Name: testUploadMyPython
Version: 1.1
Summary: Sample pip package
Home-page: UNKNOWN
Author: KHALIDH AHAMED
Author-email: khalidh.ahamed@mrcooper.com
License: MIT
Keywords: SAMPLE,FORMAT,PIP
Platform: UNKNOWN
Classifier: Development Status :: 3 - Alpha
Classifier: Intended Audience :: Developers
Classifier: Topic :: Software Development :: Build Tools
Classifier: License :: OSI Approved :: MIT License
Classifier: Programming Language :: Python :: 3.5
